app/__init__.py
app/__main__.py
app/constants.py
app/helper.py
app/scanner.py
app/validator.py
app/view.py
large_file_finder-1.0.1.dist-info/LICENSE.txt
large_file_finder-1.0.1.dist-info/METADATA
large_file_finder-1.0.1.dist-info/WHEEL
large_file_finder-1.0.1.dist-info/entry_points.txt
large_file_finder-1.0.1.dist-info/top_level.txt
large_file_finder-1.0.1.dist-info/RECORD
