Metadata-Version: 2.1
Name: large-file-finder
Version: 1.0.1
Summary: An awesome cli application to find large files in file system
Home-page: http://pypi.python.org/pypi/large-file-finder/
Author: Rahul Baruri
Author-email: rahulbaruri1@gmail.com
License: LICENSE.txt
Project-URL: Homepage, https://github.com/rbrahul/large-file-finder/
Project-URL: Source, https://github.com/rbrahul/large-file-finder/
Project-URL: Tracker, https://github.com/rbahul/large-file-finder/issues
Keywords: large,file,finder,big file,filesize,monitor,detect huge file
Platform: UNKNOWN
Requires-Python: >=3.4
License-File: LICENSE.txt
Requires-Dist: halo
Requires-Dist: tabulate
